pheno_utils/__init__.py
pheno_utils/_modidx.py
pheno_utils/age_reference_plots.py
pheno_utils/basic_analysis.py
pheno_utils/basic_plots.py
pheno_utils/blandaltman_plots.py
pheno_utils/bulk_data_loader.py
pheno_utils/cgm_plots.py
pheno_utils/cohort_selector.py
pheno_utils/config.py
pheno_utils/dates_plots.py
pheno_utils/ecg_analysis.py
pheno_utils/meta_loader.py
pheno_utils/pheno_loader.py
pheno_utils/questionnaires_handler.py
pheno_utils/sleep_plots.py
pheno_utils/config_setup/__init__.py
pheno_utils/config_setup/config_tre.json
pheno_utils/config_setup/config_tre_mbz.json
pheno_utils/config_setup/create_default_config.py
pheno_utils/config_setup/env_config.json
pheno_utils/config_setup/example_config.json
pheno_utils-0.4.0.dist-info/LICENSE
pheno_utils-0.4.0.dist-info/METADATA
pheno_utils-0.4.0.dist-info/WHEEL
pheno_utils-0.4.0.dist-info/entry_points.txt
pheno_utils-0.4.0.dist-info/top_level.txt
pheno_utils-0.4.0.dist-info/RECORD
