Metadata-Version: 2.1
Name: pheno-utils
Version: 0.4.0
Summary: Pheno data utils - viz, loaders, mergers
Home-page: https://github.com/pheno-ai/pheno-utils
Author: pheno.ai
Author-email: hagai@pheno.ai
License: Apache Software License 2.0
Keywords: nbdev jupyter notebook python
Classifier: Development Status :: 4 - Beta
Classifier: Intended Audience :: Developers
Classifier: Natural Language :: English
Classifier: Programming Language :: Python :: 3.7
Classifier: Programming Language :: Python :: 3.8
Classifier: Programming Language :: Python :: 3.9
Classifier: Programming Language :: Python :: 3.10
Classifier: License :: OSI Approved :: Apache Software License
Requires-Python: >=3.7
License-File: LICENSE
Requires-Dist: fastcore
Requires-Dist: pandas ==2.1.0
Requires-Dist: pyarrow
Requires-Dist: scipy
Requires-Dist: fastparquet
Requires-Dist: matplotlib
Requires-Dist: seaborn
Requires-Dist: scikit-learn
Requires-Dist: pyCompare
Requires-Dist: pygam
Requires-Dist: smart-open
Requires-Dist: dask[dataframe]
Requires-Dist: requests
Requires-Dist: urllib3
Provides-Extra: dev
